moclaphar/__init__.py
moclaphar/annotator/__init__.py
moclaphar/annotator/annotator.py
moclaphar/dataset/__init__.py
moclaphar/dataset/dataset.py
moclaphar/dataset/hdf5generator.py
moclaphar/dataset/io_helper.py
moclaphar/dataset/preprocess.py
moclaphar/tfhelper/__init__.py
moclaphar/tfhelper/tensorboard_helper.py
moclaphar/tfhelper/tf_helper.py
moclaphar/utils/__init__.py
moclaphar/utils/data_loader.py
moclaphar/utils/data_plotter.py
moclaphar/utils/video_segmenter.py
moclaphar-0.0.43.dist-info/METADATA
moclaphar-0.0.43.dist-info/WHEEL
moclaphar-0.0.43.dist-info/top_level.txt
moclaphar-0.0.43.dist-info/RECORD
