Metadata-Version: 2.1
Name: moclaphar
Version: 0.0.43
Summary: This packages mainly aims to make an easy process for dataset manipulation.
Home-page: https://github.com/JeiKeiLim/moclaphar
Author: Jongkuk Lim
Author-email: lim.jeikei@gmail.com
License: MIT
Platform: UNKNOWN
Classifier: Programming Language :: Python :: 3
Classifier: License :: OSI Approved :: MIT License
Classifier: Operating System :: OS Independent
Requires-Dist: scipy (>=1.4.1)
Requires-Dist: matplotlib (>=3.2.1)
Requires-Dist: seaborn (>=0.10.1)
Requires-Dist: h5py (>=2.10.0)
Requires-Dist: pandas (>=1.0.3)
Requires-Dist: moviepy (>=1.0.3)
Requires-Dist: tqdm (>=4.46.0)
Requires-Dist: opencv-python (>=4.2.0)
